odoo/addons/product_multi_barcode_constraint_per_company/README.rst
odoo/addons/product_multi_barcode_constraint_per_company/__init__.py
odoo/addons/product_multi_barcode_constraint_per_company/__manifest__.py
odoo/addons/product_multi_barcode_constraint_per_company/i18n/it.po
odoo/addons/product_multi_barcode_constraint_per_company/i18n/product_multi_barcode_constraint_per_company.pot
odoo/addons/product_multi_barcode_constraint_per_company/models/__init__.py
odoo/addons/product_multi_barcode_constraint_per_company/models/product_barcode.py
odoo/addons/product_multi_barcode_constraint_per_company/readme/DESCRIPTION.rst
odoo/addons/product_multi_barcode_constraint_per_company/security/ir_rule.xml
odoo/addons/product_multi_barcode_constraint_per_company/static/description/icon.png
odoo/addons/product_multi_barcode_constraint_per_company/static/description/index.html
odoo_addon_product_multi_barcode_constraint_per_company-16.0.1.0.1.2.dist-info/METADATA
odoo_addon_product_multi_barcode_constraint_per_company-16.0.1.0.1.2.dist-info/WHEEL
odoo_addon_product_multi_barcode_constraint_per_company-16.0.1.0.1.2.dist-info/top_level.txt
odoo_addon_product_multi_barcode_constraint_per_company-16.0.1.0.1.2.dist-info/RECORD
