Metadata-Version: 2.1
Name: odoo-addon-product-multi-barcode-constraint-per-company
Version: 16.0.1.0.1.2
Summary: Glue module for product_multi_barcode andproduct_barcode_constraint_per_company
Home-page: https://github.com/OCA/stock-logistics-barcode
Author: akretion, Odoo Community Association (OCA)
Author-email: support@odoo-community.org
License: AGPL-3
Platform: UNKNOWN
Classifier: Programming Language :: Python
Classifier: Framework :: Odoo
Classifier: Framework :: Odoo :: 16.0
Classifier: License :: OSI Approved :: GNU Affero General Public License v3
Requires-Python: >=3.10
Requires-Dist: odoo-addon-product-barcode-constraint-per-company <16.1dev,>=16.0dev
Requires-Dist: odoo-addon-product-multi-barcode <16.1dev,>=16.0dev
Requires-Dist: odoo <16.1dev,>=16.0a
